dataExplore/__init__.py
dataExplore/builder.py
dataExplore/dataExplorer.py
dataExplore/director.py
dataExplore/main.py
dataExploreNew/__init__.py
dataExploreNew/builder.py
dataExploreNew/dataExplorer.py
dataExploreNew/director.py
dataExploreNew/main.py
dataExploreNew-0.5.dist-info/LICENSE.txt
dataExploreNew-0.5.dist-info/METADATA
dataExploreNew-0.5.dist-info/WHEEL
dataExploreNew-0.5.dist-info/top_level.txt
dataExploreNew-0.5.dist-info/RECORD
